cld3.cpython-36m-darwin.so
cld3-0.2.2.dist-info/DESCRIPTION.rst
cld3-0.2.2.dist-info/METADATA
cld3-0.2.2.dist-info/RECORD
cld3-0.2.2.dist-info/WHEEL
cld3-0.2.2.dist-info/metadata.json
cld3-0.2.2.dist-info/top_level.txt
