Metadata-Version: 2.0
Name: cld3
Version: 0.2.2
Summary: CLD3 Python bindings
Home-page: https://github.com/Elizafox/cld3
Author: Google, Johannes Baiter, Elizabeth Myers
Author-email: elizabeth@interlinked.me
License: Apache2
Keywords: cld3,cffi
Platform: UNKNOWN
